causaldmir/__init__.py
causaldmir/datasets/__init__.py
causaldmir/datasets/simlulators.py
causaldmir/datasets/utils.py
causaldmir/discovery/__init__.py
causaldmir/discovery/_base_discovery_model.py
causaldmir/discovery/constraint/__init__.py
causaldmir/discovery/constraint/adjacency_search.py
causaldmir/discovery/constraint/pc.py
causaldmir/discovery/funtional_based/__init__.py
causaldmir/discovery/funtional_based/LearningHierarchicalStructure/Causal_Discovery_in_LHM.py
causaldmir/discovery/funtional_based/LearningHierarchicalStructure/FindCausalCluster.py
causaldmir/discovery/funtional_based/LearningHierarchicalStructure/GIN2.py
causaldmir/discovery/funtional_based/LearningHierarchicalStructure/HSIC.py
causaldmir/discovery/funtional_based/LearningHierarchicalStructure/Infer_Causal_Order.py
causaldmir/discovery/funtional_based/LearningHierarchicalStructure/MakeGraph.py
causaldmir/discovery/funtional_based/LearningHierarchicalStructure/MergeCluster.py
causaldmir/discovery/funtional_based/LearningHierarchicalStructure/MergeCluster_backup.py
causaldmir/discovery/funtional_based/LearningHierarchicalStructure/Orientation.py
causaldmir/discovery/funtional_based/LearningHierarchicalStructure/Overlap_Merge.py
causaldmir/discovery/funtional_based/LearningHierarchicalStructure/Paper_simulation.py
causaldmir/discovery/funtional_based/LearningHierarchicalStructure/TetradMethod.py
causaldmir/discovery/funtional_based/LearningHierarchicalStructure/UpdataData.py
causaldmir/discovery/funtional_based/LearningHierarchicalStructure/Utils.py
causaldmir/discovery/funtional_based/LearningHierarchicalStructure/VanishedTest.py
causaldmir/discovery/funtional_based/LearningHierarchicalStructure/__init__.py
causaldmir/discovery/funtional_based/LearningHierarchicalStructure/independence.py
causaldmir/discovery/funtional_based/LearningHierarchicalStructure/mutual.py
causaldmir/discovery/funtional_based/LearningHierarchicalStructure/test_LHS.py
causal_dmir-0.0.4.dist-info/METADATA
causal_dmir-0.0.4.dist-info/WHEEL
causal_dmir-0.0.4.dist-info/top_level.txt
causal_dmir-0.0.4.dist-info/RECORD
